tendrl/__init__.py
tendrl/client.py
tendrl/models.py
tendrl/storage.py
tendrl/utils/__init__.py
tendrl/utils/utils.py
tendrl-0.1.6.dist-info/licenses/LICENSE
tendrl-0.1.6.dist-info/METADATA
tendrl-0.1.6.dist-info/WHEEL
tendrl-0.1.6.dist-info/top_level.txt
tendrl-0.1.6.dist-info/RECORD
