Metadata-Version: 2.4
Name: tendrl
Version: 0.1.6
Summary: A Python SDK for the Tendrl data collection platform with cross-platform UNIX socket support, offline storage, and dynamic batching. Licensed for use with Tendrl services only.
Home-page: https://github.com/tendrl-inc-labs/python-sdk
Author: Tendrl
Author-email: support@tendrl.com
Project-URL: Bug Tracker, https://github.com/tendrl-inc-labs/python-sdk/issues
Project-URL: Documentation, https://tendrl.com/docs/python_sdk/
Project-URL: Source Code, https://github.com/tendrl-inc-labs/python-sdk
Project-URL: License, https://github.com/tendrl-inc-labs/python-sdk/blob/main/LICENSE
Keywords: telemetry IoT monitoring data-collection agent sdk unix-socket batching offline-storage
Classifier: Development Status :: 4 - Beta
Classifier: Intended Audience :: Developers
Classifier: Topic :: Software Development :: Libraries :: Python Modules
Classifier: Topic :: System :: Monitoring
Classifier: Topic :: System :: Logging
Classifier: Topic :: System :: Networking :: Monitoring
Classifier: Topic :: Internet
Classifier: License :: Other/Proprietary License
Classifier: Programming Language :: Python :: 3
Classifier: Programming Language :: Python :: 3.8
Classifier: Programming Language :: Python :: 3.9
Classifier: Programming Language :: Python :: 3.10
Classifier: Programming Language :: Python :: 3.11
Classifier: Programming Language :: Python :: 3.12
Classifier: Operating System :: OS Independent
Classifier: Operating System :: Microsoft :: Windows :: Windows 10
Classifier: Operating System :: POSIX :: Linux
Classifier: Operating System :: MacOS
Requires-Python: >=3.8
License-File: LICENSE
Requires-Dist: httpx[http2]==0.28.1
Requires-Dist: psutil==7.0.0
Provides-Extra: dev
Requires-Dist: pytest>=7.0; extra == "dev"
Requires-Dist: pytest-asyncio>=0.21; extra == "dev"
Requires-Dist: black>=22.0; extra == "dev"
Requires-Dist: flake8>=4.0; extra == "dev"
Requires-Dist: mypy>=1.0; extra == "dev"
Dynamic: author
Dynamic: author-email
Dynamic: classifier
Dynamic: description
Dynamic: description-content-type
Dynamic: home-page
Dynamic: keywords
Dynamic: license-file
Dynamic: project-url
Dynamic: provides-extra
Dynamic: requires-dist
Dynamic: requires-python
Dynamic: summary
